odoo/addons/base_edi/README.rst
odoo/addons/base_edi/__init__.py
odoo/addons/base_edi/__manifest__.py
odoo/addons/base_edi/data/module_category.xml
odoo/addons/base_edi/i18n/base_edi.pot
odoo/addons/base_edi/i18n/nl.po
odoo/addons/base_edi/readme/CONTRIBUTORS.rst
odoo/addons/base_edi/readme/DESCRIPTION.rst
odoo/addons/base_edi/readme/ROADMAP.rst
odoo/addons/base_edi/security/edi_groups.xml
odoo/addons/base_edi/static/description/icon.png
odoo/addons/base_edi/static/description/icon.svg
odoo/addons/base_edi/static/description/index.html
odoo/addons/base_edi/views/edi_menu.xml
odoo13_addon_base_edi-13.0.1.0.2.dist-info/METADATA
odoo13_addon_base_edi-13.0.1.0.2.dist-info/WHEEL
odoo13_addon_base_edi-13.0.1.0.2.dist-info/top_level.txt
odoo13_addon_base_edi-13.0.1.0.2.dist-info/RECORD
